SentralTimetable/__init__.py
SentralTimetable/credentials.py
SentralTimetable/objects.py
SentralTimetable/scrapers.py
SentralTimetable/timetable.py
SentralTimetable/webdriver.py
SentralTimetable-2022.0.7.dist-info/LICENSE.md
SentralTimetable-2022.0.7.dist-info/METADATA
SentralTimetable-2022.0.7.dist-info/WHEEL
SentralTimetable-2022.0.7.dist-info/top_level.txt
SentralTimetable-2022.0.7.dist-info/RECORD
