Metadata-Version: 2.1
Name: SentralTimetable
Version: 2022.0.7
Summary: A tool to get your timetable from Sentral.
Home-page: https://github.com/J-J-B-J/get-sentral
Author: SuperHarmony910 and J-J-B-J
Keywords: Sentral school timetable python scraper
Platform: Windows
Platform: MacOS
Platform: Unix
Classifier: Development Status :: 5 - Production/Stable
Classifier: Intended Audience :: Education
Classifier: Intended Audience :: Developers
Classifier: License :: Other/Proprietary License
Classifier: Natural Language :: English
Classifier: Environment :: Console
Classifier: Environment :: Web Environment
Classifier: Programming Language :: Python :: 3
Classifier: Operating System :: MacOS
Classifier: Operating System :: Microsoft :: Windows
Classifier: Operating System :: Unix
Classifier: Topic :: Education
Classifier: Topic :: Software Development
Classifier: Topic :: Software Development :: Libraries :: Python Modules
Requires-Python: >=3.9
License-File: LICENSE.md
Requires-Dist: bs4 (~=0.0.1)
Requires-Dist: beautifulsoup4 (~=4.10.0)
Requires-Dist: selenium (~=4.4.2)
Requires-Dist: TextBarcodeGenerator (~=2022.0.2)
Requires-Dist: pyinstaller (~=5.6.2)
Requires-Dist: webdriver-manager (~=3.8.3)
Requires-Dist: python-dotenv (~=0.20.0)
Requires-Dist: setuptools (~=61.3.0)
Requires-Dist: Pillow (~=9.0.1)
